<?xml version="1.0" encoding="UTF-8"?>
<data xmlns="http://www.woltlab.com" xmlns:xsi="http://www.w3.org/2001/XMLSchema-instance" xsi:schemaLocation="http://www.woltlab.com http://www.woltlab.com/XSD/maelstrom/option.xsd">
	<import>
		<categories>
			<category name="aboutMe">
				<parent>general</parent>
			</category>
		</categories>
	
		<options>
			<option name="aboutMe_title">
				<categoryname>aboutMe</categoryname>
				<optiontype>textI18n</optiontype>
				<supporti18n>1</supporti18n>
				<defaultvalue><![CDATA[Über uns]]></defaultvalue>
			</option>
			<option name="aboutMe_description">
				<categoryname>aboutMe</categoryname>
				<optiontype>textI18n</optiontype>
				<supporti18n>1</supporti18n>
				<defaultvalue><![CDATA[Lernen Sie uns kennen]]></defaultvalue>
			</option>
			<option name="aboutMe_headline">
				<categoryname>aboutMe</categoryname>
				<optiontype>textI18n</optiontype>
				<supporti18n>1</supporti18n>
				<defaultvalue><![CDATA[Über uns]]></defaultvalue>
			</option>
			<option name="aboutMe_content">
				<categoryname>aboutMe</categoryname>
				<optiontype>textareaI18n</optiontype>
				<supporti18n>1</supporti18n>
				<defaultvalue><![CDATA[Hier könnte Ihre Beschreibung stehen]]></defaultvalue>
			</option>
			<option name="aboutMe_content_enable_html">
				<categoryname>aboutMe</categoryname>
				<optiontype>boolean</optiontype>
			</option>
		</options>
	</import>
</data>